template_handler/__init__.py
template_handler/custom.py
template_handler/formatted_yaml.py
sceptre_formatted_yaml_handler-1.0.0.dist-info/METADATA
sceptre_formatted_yaml_handler-1.0.0.dist-info/WHEEL
sceptre_formatted_yaml_handler-1.0.0.dist-info/entry_points.txt
sceptre_formatted_yaml_handler-1.0.0.dist-info/RECORD
