Metadata-Version: 2.1
Name: sceptre-formatted-yaml-handler
Version: 1.0.0
Summary: A Sceptre template handler for opinionated formatted YAML
Home-page: https://github.com/Sceptre/sceptre-formatted-yaml-handler
License: Apache-2.0
Keywords: sceptre,sceptre-handler
Author: Mitchell Rowling
Author-email: 57084321+mrowlingfox@users.noreply.github.com
Requires-Python: >=3.8,<4.0
Classifier: Environment :: Console
Classifier: Intended Audience :: Developers
Classifier: License :: OSI Approved :: Apache Software License
Classifier: Natural Language :: English
Classifier: Programming Language :: Python :: 3
Classifier: Programming Language :: Python :: 3.8
Classifier: Programming Language :: Python :: 3.9
Classifier: Programming Language :: Python :: 3.10
Classifier: Programming Language :: Python :: 3.11
Classifier: Programming Language :: Python :: 3.12
Project-URL: Repository, https://github.com/Sceptre/sceptre-formatted-yaml-handler
